FunctionalProgrammingInPython/README.md
FunctionalProgrammingInPython/__init__.py
FunctionalProgrammingInPython/__main__.py
FunctionalProgrammingInPython/file.epub
FunctionalProgrammingInPython/index.html
FunctionalProgrammingInPython/css/__init__.py
FunctionalProgrammingInPython/css/annotations.css
FunctionalProgrammingInPython/css/main.css
FunctionalProgrammingInPython/css/normalize.css
FunctionalProgrammingInPython/css/popup.css
FunctionalProgrammingInPython/font/__init__.py
FunctionalProgrammingInPython/font/fontello.eot
FunctionalProgrammingInPython/font/fontello.svg
FunctionalProgrammingInPython/font/fontello.ttf
FunctionalProgrammingInPython/font/fontello.woff
FunctionalProgrammingInPython/img/__init__.py
FunctionalProgrammingInPython/img/annotator-glyph-sprite.png
FunctionalProgrammingInPython/img/annotator-icon-sprite.png
FunctionalProgrammingInPython/img/apple-touch-icon.png
FunctionalProgrammingInPython/img/cancelfullscreen.png
FunctionalProgrammingInPython/img/close.png
FunctionalProgrammingInPython/img/fullscreen.png
FunctionalProgrammingInPython/img/loader.gif
FunctionalProgrammingInPython/img/menu-icon.png
FunctionalProgrammingInPython/img/save.png
FunctionalProgrammingInPython/img/saved.png
FunctionalProgrammingInPython/img/settings-s.png
FunctionalProgrammingInPython/img/settings.png
FunctionalProgrammingInPython/img/star.png
FunctionalProgrammingInPython/js/__init__.py
FunctionalProgrammingInPython/js/epub.js
FunctionalProgrammingInPython/js/epub.min.js
FunctionalProgrammingInPython/js/epub.min.map
FunctionalProgrammingInPython/js/hooks.min.js
FunctionalProgrammingInPython/js/hooks.min.map
FunctionalProgrammingInPython/js/reader.js
FunctionalProgrammingInPython/js/reader.js.map
FunctionalProgrammingInPython/js/reader.min.js
FunctionalProgrammingInPython/js/reader.min.map
FunctionalProgrammingInPython/js/hooks/__init__.py
FunctionalProgrammingInPython/js/hooks/extensions/__init__.py
FunctionalProgrammingInPython/js/hooks/extensions/highlight.js
functional_programming_in_python-2024.3.2.0.dist-info/METADATA
functional_programming_in_python-2024.3.2.0.dist-info/WHEEL
functional_programming_in_python-2024.3.2.0.dist-info/entry_points.txt
functional_programming_in_python-2024.3.2.0.dist-info/top_level.txt
functional_programming_in_python-2024.3.2.0.dist-info/RECORD
